CrocodilesEncryptor/CrocodilesEncryptor.py
CrocodilesEncryptor/__init__.py
CrocodilesEncryptor-1.0.0.dist-info/LICENSE
CrocodilesEncryptor-1.0.0.dist-info/METADATA
CrocodilesEncryptor-1.0.0.dist-info/WHEEL
CrocodilesEncryptor-1.0.0.dist-info/top_level.txt
CrocodilesEncryptor-1.0.0.dist-info/RECORD
